energy_efficient_cnn.v
`timescale 1ns / 1ps

module energy_efficient_cnn (
    input wire clk,
    input wire rst,
    input wire [63:0] image_input, // 8x8 image, 1-bit per pixel
    input wire start,
    output reg [3:0] classification,
    output reg done
);

    // Parameters
    parameter INPUT_SIZE = 64;
    parameter CONV1_FILTERS = 4;
    parameter CONV1_SIZE = 3;
    parameter POOL_SIZE = 2;
    parameter FC_NEURONS = 10;

    // Internal signals
    reg [7:0] quantized_input [63:0];
    reg [7:0] conv1_output [3:0][35:0]; // 6x6 output for each filter
    reg [7:0] pool_output [3:0][8:0];  // 3x3 output for each filter
    reg [7:0] fc_output [9:0];

    // Clock gating signals
    reg conv1_clk_en, pool_clk_en, fc_clk_en;
    wire gated_conv1_clk, gated_pool_clk, gated_fc_clk;

    // Power gating signals
    reg conv1_power_en, pool_power_en, fc_power_en;

    // State machine
    reg [2:0] state;
    parameter IDLE = 3'd0, QUANTIZE = 3'd1, CONV1 = 3'd2, POOL = 3'd3, FC = 3'd4, DONE = 3'd5;

    // Clock gating
    assign gated_conv1_clk = clk & conv1_clk_en;
    assign gated_pool_clk = clk & pool_clk_en;
    assign gated_fc_clk = clk & fc_clk_en;

    // Quantization
    integer i, j, f;
    always @(posedge clk or posedge rst) begin
        if (rst) begin
            for (i = 0; i < INPUT_SIZE; i = i + 1) begin
                quantized_input[i] <= 8'd0;
            end
        end else if (state == QUANTIZE) begin
            for (i = 0; i < INPUT_SIZE; i = i + 1) begin
                quantized_input[i] <= image_input[i] ? 8'd255 : 8'd0;
            end
        end
    end

    // Convolution layer (simplified depthwise separable convolution)
    always @(posedge gated_conv1_clk or posedge rst) begin
        if (rst) begin
            for (f = 0; f < CONV1_FILTERS; f = f + 1) begin
                for (i = 0; i < 36; i = i + 1) begin
                    conv1_output[f][i] <= 8'd0;
                end
            end
        end else if (state == CONV1 && conv1_power_en) begin
            // Implement depthwise separable convolution here
            // This is a simplified version, you'd need to implement the actual convolution
            for (f = 0; f < CONV1_FILTERS; f = f + 1) begin
                for (i = 0; i < 6; i = i + 1) begin
                    for (j = 0; j < 6; j = j + 1) begin
                        conv1_output[f][i*6+j] <= quantized_input[(i+1)*8+j+1];
                    end
                end
            end
        end
    end

    // Pooling layer
    always @(posedge gated_pool_clk or posedge rst) begin
        if (rst) begin
            for (f = 0; f < CONV1_FILTERS; f = f + 1) begin
                for (i = 0; i < 9; i = i + 1) begin
                    pool_output[f][i] <= 8'd0;
                end
            end
        end else if (state == POOL && pool_power_en) begin
            for (f = 0; f < CONV1_FILTERS; f = f + 1) begin
                for (i = 0; i < 3; i = i + 1) begin
                    for (j = 0; j < 3; j = j + 1) begin
                        pool_output[f][i*3+j] <= max(max(conv1_output[f][i*12+j*2], conv1_output[f][i*12+j*2+1]),
                                                     max(conv1_output[f][(i*2+1)*6+j*2], conv1_output[f][(i*2+1)*6+j*2+1]));
                    end
                end
            end
        end
    end

    // Fully connected layer
    always @(posedge gated_fc_clk or posedge rst) begin
        if (rst) begin
            for (i = 0; i < FC_NEURONS; i = i + 1) begin
                fc_output[i] <= 8'd0;
            end
        end else if (state == FC && fc_power_en) begin
            // Implement fully connected layer here
            // This is a simplified version, you'd need to implement the actual matrix multiplication
            for (i = 0; i < FC_NEURONS; i = i + 1) begin
                fc_output[i] <= pool_output[i % CONV1_FILTERS][i / CONV1_FILTERS];
            end
        end
    end

    // State machine and control logic
    always @(posedge clk or posedge rst) begin
        if (rst) begin
            state <= IDLE;
            classification <= 4'd0;
            done <= 1'b0;
            conv1_clk_en <= 1'b0;
            pool_clk_en <= 1'b0;
            fc_clk_en <= 1'b0;
            conv1_power_en <= 1'b0;
            pool_power_en <= 1'b0;
            fc_power_en <= 1'b0;
        end else begin
            case (state)
                IDLE: begin
                    if (start) begin
                        state <= QUANTIZE;
                        done <= 1'b0;
                    end
                end
                QUANTIZE: begin
                    state <= CONV1;
                    conv1_clk_en <= 1'b1;
                    conv1_power_en <= 1'b1;
                end
                CONV1: begin
                    state <= POOL;
                    conv1_clk_en <= 1'b0;
                    pool_clk_en <= 1'b1;
                    pool_power_en <= 1'b1;
                end
                POOL: begin
                    state <= FC;
                    pool_clk_en <= 1'b0;
                    fc_clk_en <= 1'b1;
                    fc_power_en <= 1'b1;
                end
                FC: begin
                    state <= DONE;
                    fc_clk_en <= 1'b0;
                end
                DONE: begin
                    classification <= get_max_index(fc_output[0], fc_output[1], fc_output[2], fc_output[3],
                                                    fc_output[4], fc_output[5], fc_output[6], fc_output[7],
                                                    fc_output[8], fc_output[9]);
                    done <= 1'b1;
                    state <= IDLE;
                    conv1_power_en <= 1'b0;
                    pool_power_en <= 1'b0;
                    fc_power_en <= 1'b0;
                end
            endcase
        end
    end

    // Helper functions
    function [7:0] max;
        input [7:0] a, b;
    begin
        max = (a > b) ? a : b;
    end
    endfunction

    function [3:0] get_max_index;
        input [7:0] v0, v1, v2, v3, v4, v5, v6, v7, v8, v9;
        reg [7:0] max_val;
        reg [3:0] max_idx;
        integer k;
    begin
        max_val = v0;
        max_idx = 4'd0;
        if (v1 > max_val) begin max_val = v1; max_idx = 4'd1; end
        if (v2 > max_val) begin max_val = v2; max_idx = 4'd2; end
        if (v3 > max_val) begin max_val = v3; max_idx = 4'd3; end
        if (v4 > max_val) begin max_val = v4; max_idx = 4'd4; end
        if (v5 > max_val) begin max_val = v5; max_idx = 4'd5; end
        if (v6 > max_val) begin max_val = v6; max_idx = 4'd6; end
        if (v7 > max_val) begin max_val = v7; max_idx = 4'd7; end
        if (v8 > max_val) begin max_val = v8; max_idx = 4'd8; end
        if (v9 > max_val) begin max_val = v9; max_idx = 4'd9; end
        get_max_index = max_idx;
    end
    endfunction

endmodule

energy_efficient_cnn_tb.v
`timescale 1ns / 1ps

module energy_efficient_cnn_tb;

    reg clk;
    reg rst;
    reg [63:0] image_input;
    reg start;
    wire [3:0] classification;
    wire done;

    // Instantiate the Unit Under Test (UUT)
    energy_efficient_cnn uut (
        .clk(clk),
        .rst(rst),
        .image_input(image_input),
        .start(start),
        .classification(classification),
        .done(done)
    );

    // Clock generation
    initial begin
        clk = 0;
        forever #5 clk = ~clk;  // 100MHz clock
    end

    // Test stimulus
    initial begin
        // Initialize inputs
        rst = 1;
        image_input = 0;
        start = 0;

        // Reset
        #100;
        rst = 0;

        // Test case 1: Simple image (all zeros except one pixel)
        #10;
        image_input = 64'h0000000000000080;  // Single pixel set in the last row
        start = 1;
        #10;
        start = 0;

        // Wait for processing to complete
        wait(done);
        $display("Test case 1 - Classification: %d", classification);

        // Test case 2: Different image pattern
        #100;
        image_input = 64'h00FF00FF00FF00FF;  // Alternating rows of all on/off pixels
        start = 1;
        #10;
        start = 0;

        // Wait for processing to complete
        wait(done);
        $display("Test case 2 - Classification: %d", classification);

        // Add more test cases as needed

        // End simulation
        #100;
        $finish;
    end

    // Optional: Uncomment to generate VCD file for waveform viewing
    initial begin
         $dumpfile("waveform.vcd");
         $dumpvars(0, energy_efficient_cnn_tb);
    end

endmodule

waveform.vcd
$date
	Wed Oct 16 13:36:20 2024
$end
$version
	Icarus Verilog
$end
$timescale
	1ps
$end
$scope module energy_efficient_cnn_tb $end
$var wire 1 ! done $end
$var wire 4 " classification [3:0] $end
$var reg 1 # clk $end
$var reg 64 $ image_input [63:0] $end
$var reg 1 % rst $end
$var reg 1 & start $end
$scope module uut $end
$var wire 1 # clk $end
$var wire 1 ' gated_conv1_clk $end
$var wire 1 ( gated_fc_clk $end
$var wire 1 ) gated_pool_clk $end
$var wire 64 * image_input [63:0] $end
$var wire 1 % rst $end
$var wire 1 & start $end
$var parameter 3 + CONV1 $end
$var parameter 32 , CONV1_FILTERS $end
$var parameter 32 - CONV1_SIZE $end
$var parameter 3 . DONE $end
$var parameter 3 / FC $end
$var parameter 32 0 FC_NEURONS $end
$var parameter 3 1 IDLE $end
$var parameter 32 2 INPUT_SIZE $end
$var parameter 3 3 POOL $end
$var parameter 32 4 POOL_SIZE $end
$var parameter 3 5 QUANTIZE $end
$var reg 4 6 classification [3:0] $end
$var reg 1 7 conv1_clk_en $end
$var reg 1 8 conv1_power_en $end
$var reg 1 ! done $end
$var reg 1 9 fc_clk_en $end
$var reg 1 : fc_power_en $end
$var reg 1 ; pool_clk_en $end
$var reg 1 < pool_power_en $end
$var reg 3 = state [2:0] $end
$var integer 32 > f [31:0] $end
$var integer 32 ? i [31:0] $end
$var integer 32 @ j [31:0] $end
$scope function get_max_index $end
$var reg 4 A max_idx [3:0] $end
$var reg 8 B max_val [7:0] $end
$var reg 8 C v0 [7:0] $end
$var reg 8 D v1 [7:0] $end
$var reg 8 E v2 [7:0] $end
$var reg 8 F v3 [7:0] $end
$var reg 8 G v4 [7:0] $end
$var reg 8 H v5 [7:0] $end
$var reg 8 I v6 [7:0] $end
$var reg 8 J v7 [7:0] $end
$var reg 8 K v8 [7:0] $end
$var reg 8 L v9 [7:0] $end
$upscope $end
$scope function max $end
$var reg 8 M a [7:0] $end
$var reg 8 N b [7:0] $end
$upscope $end
$upscope $end
$upscope $end
$enddefinitions $end
$comment Show the parameter values. $end
$dumpall
b1 5
b10 4
b11 3
b1000000 2
b0 1
b1010 0
b100 /
b101 .
b11 -
b100 ,
b10 +
$end
#0
$dumpvars
bx N
bx M
bx L
bx K
bx J
bx I
bx H
bx G
bx F
bx E
bx D
bx C
bx B
bx A
bx @
b1000000 ?
b100 >
b0 =
0<
0;
0:
09
08
07
b0 6
b0 *
0)
0(
0'
0&
1%
b0 $
0#
b0 "
0!
$end
#5000
b1000000 ?
1#
#10000
0#
#15000
b1000000 ?
1#
#20000
0#
#25000
b1000000 ?
1#
#30000
0#
#35000
b1000000 ?
1#
#40000
0#
#45000
b1000000 ?
1#
#50000
0#
#55000
b1000000 ?
1#
#60000
0#
#65000
b1000000 ?
1#
#70000
0#
#75000
b1000000 ?
1#
#80000
0#
#85000
b1000000 ?
1#
#90000
0#
#95000
b1000000 ?
1#
#100000
0#
0%
#105000
1#
#110000
0#
1&
b10000000 $
b10000000 *
#115000
b1 =
1#
#120000
0#
0&
#125000
b110 @
b100 >
1'
18
17
b10 =
b110 ?
1#
#130000
0'
0#
#135000
b0 M
b0 N
1)
1<
1;
07
b11 =
b11 @
b11 ?
b100 >
0'
1#
#140000
0)
0#
#145000
1(
1:
19
0;
b100 =
b11 @
b1010 ?
b100 >
0)
1#
#150000
0(
0#
#155000
09
b101 =
b1010 ?
0(
1#
#160000
0#
#165000
0:
0<
08
b0 =
1!
b0 A
b0 B
b0 C
b0 D
b0 E
b0 F
b0 G
b0 H
b0 I
b0 J
b0 K
b0 L
1#
#170000
0#
#175000
1#
#180000
0#
#185000
1#
#190000
0#
#195000
1#
#200000
0#
#205000
1#
#210000
0#
#215000
1#
#220000
0#
#225000
1#
#230000
0#
#235000
1#
#240000
0#
#245000
1#
#250000
0#
#255000
1#
#260000
0#
#265000
0!
b1 =
1#
1&
b11111111000000001111111100000000111111110000000011111111 $
b11111111000000001111111100000000111111110000000011111111 *
#270000
0#
#275000
b110 @
b100 >
1'
18
17
b10 =
b110 ?
1#
0&
#280000
0'
0#
#285000
b0 M
b11111111 N
1)
1<
1;
07
b11 =
b11 @
b11 ?
b100 >
0'
1#
#290000
0)
0#
#295000
1(
1:
19
0;
b100 =
b0 M
b11111111 N
b11 @
b1010 ?
b100 >
0)
1#
#300000
0(
0#
#305000
09
b101 =
b1010 ?
0(
1#
#310000
0#
#315000
0:
0<
08
b0 =
1!
b11111111 B
b11111111 C
b11111111 D
b11111111 E
b11111111 F
b11111111 G
b11111111 H
b11111111 I
b11111111 J
b11111111 K
b11111111 L
1#
